gen3git.py
gen3git-0.8.1.dist-info/METADATA
gen3git-0.8.1.dist-info/WHEEL
gen3git-0.8.1.dist-info/licenses/LICENSE
gen3git-0.8.1.dist-info/licenses/NOTICE
gen3git-0.8.1.dist-info/RECORD
