Metadata-Version: 2.4
Name: gen3git
Version: 0.8.1
Summary: Utilities to help with versioning and releasing
License: Apache-2.0
License-File: LICENSE
License-File: NOTICE
Author: Center for Translational Data Science at the University of Chicago
Author-email: support@gen3.org
Requires-Python: >=3.13,<4.0
Classifier: License :: OSI Approved :: Apache Software License
Classifier: Programming Language :: Python :: 3
Classifier: Programming Language :: Python :: 3.13
Classifier: Programming Language :: Python :: 3.14
Requires-Dist: gitpython (>=3.1.46)
Requires-Dist: packaging (>=25.0)
Requires-Dist: pygithub (>=2.8.1)
Requires-Dist: pytz (>=2025.2)
Requires-Dist: requests (>=2.32.5)
